skikitlean/xlwinxxx.py
skikitlean-0.2.dist-info/METADATA
skikitlean-0.2.dist-info/WHEEL
skikitlean-0.2.dist-info/top_level.txt
skikitlean-0.2.dist-info/RECORD
