Metadata-Version: 2.4
Name: skikitlean
Version: 0.2
Summary: skikitlean
Author-email: lolikuzi98@gmail.com
Dynamic: author-email
Dynamic: summary
